Metadata-Version: 2.1
Name: sage_numerical_backends_coin
Version: 10.4
Summary: COIN-OR backend for Sage MixedIntegerLinearProgram
Home-page: https://github.com/mkoeppe/sage-numerical-backends-coin
Author: Nathann Cohen, Yuan Zhou, John Perry, Zeyi Wang, Martin Albrecht, Jori Mäntysalo, Matthias Koeppe, Erik M. Bray, Jeroen Demeyer, Nils Bruin, Julien Puydt, Dima Pasechnik, and others
Author-email: mkoeppe@math.ucdavis.edu
License: GPLv2+
Keywords: milp,linear-programming,optimization
Classifier: Development Status :: 5 - Production/Stable
Classifier: Intended Audience :: Science/Research
Classifier: License :: OSI Approved :: GNU General Public License v2 or later (GPLv2+)
Classifier: Programming Language :: Python
Classifier: Programming Language :: Python :: 3
Classifier: Programming Language :: Python :: 3.6
Classifier: Programming Language :: Python :: 3.7
Classifier: Programming Language :: Python :: 3.8
Classifier: Programming Language :: Python :: 3.9
Classifier: Programming Language :: Python :: 3.10
Classifier: Programming Language :: Python :: 3.11
Classifier: Programming Language :: Python :: 3.12
License-File: LICENSE
Requires-Dist: sphinx
